azure_face_api
